{"MI/y5vTS/oaV3mVfdLhhYQ==":"mbr.jpg","RySyrkUrrPZPhzdrNWLxhg==":"mbr.jpeg","IedBUMFPy/wdQmKABiOf4g==":"mbr-1.jpg","X30aVRBEqsZY/bFEWmkiVg==":"mbr-2.jpg","YNiXBWgwNOjqA22Dmwqb5g==":"mbr-3.jpg","DrFPsfmeg5oSTFbYnhLeYw==":"mbr-4.jpg","6OY4DwgD2obALVw0F7NFIw==":"mbr-5.jpg","uEGJd4PrLTvFpgfDvYs4Lg==":"mbr-6.jpg","XRDdhODpZEaMtrsqfQDByg==":"mbr-7.jpg","+CFTCwDQuqe5qZvoVm36lQ==":"mbr-8.jpg","h65qWKc1x44MCIjo54okNQ==":"mbr-696x451.jpg","9boIVwzmCM+ODfQHPeeQdQ==":"mbr-696x696.jpg","xT2Ih6zX2hIuVNKJgzWt9A==":"mbr-696x486.jpg","QStYAyYzwFDmBKCVn9BR4g==":"mbr-1920x1440.jpg","v1J5QsqMfvSHmkOXhYSXWA==":"mbr-1-1920x1440.jpg","2CkWFC7sgHiDvn8pOEv+vA==":"mbr-1920x1272.jpg","bmvRjkn0z3RLfxisP2SqRg==":"mbr-2-1920x1440.jpg","gOHNFCFzquIwSvEVda+eXw==":"litery-swietlne-led-1-524x349.jpg","EVwBtLI2XG1zMqldtwiHYA==":"img_20210811-235907-524x699.jpeg","tbXszupJ2Kc0K3cVTAEGpQ==":"produkcja_scenografii_poznan-524x296.jpeg","Ms1rg7WDHcEjClWCfh3ufg==":"img_20211101-122854-524x632.jpeg"}